[
  {
    "period": "114051287",
    "drawNumbers": [
      5,
      10,
      8,
      1,
      3,
      9,
      4,
      6,
      7,
      2
    ],
    "drawDate": "2025-09-10T00:00:00",
    "drawTime": "17:55",
    "dataSource": "python-scraper",
    "isValid": true,
    "scrapedAt": "2025-09-10T17:57:50.429228"
  },
  {
    "period": "114051286",
    "drawNumbers": [
      8,
      6,
      4,
      5,
      2,
      10,
      3,
      1,
      9,
      7
    ],
    "drawDate": "2025-09-10T00:00:00",
    "drawTime": "17:50",
    "dataSource": "python-scraper",
    "isValid": true,
    "scrapedAt": "2025-09-10T17:57:50.429236"
  },
  {
    "period": "114051285",
    "drawNumbers": [
      7,
      6,
      3,
      5,
      1,
      4,
      8,
      10,
      9,
      2
    ],
    "drawDate": "2025-09-10T00:00:00",
    "drawTime": "17:45",
    "dataSource": "python-scraper",
    "isValid": true,
    "scrapedAt": "2025-09-10T17:57:50.429240"
  },
  {
    "period": "114051284",
    "drawNumbers": [
      4,
      9,
      7,
      1,
      6,
      10,
      2,
      8,
      3,
      5
    ],
    "drawDate": "2025-09-10T00:00:00",
    "drawTime": "17:40",
    "dataSource": "python-scraper",
    "isValid": true,
    "scrapedAt": "2025-09-10T17:57:50.429244"
  },
  {
    "period": "114051283",
    "drawNumbers": [
      4,
      3,
      8,
      7,
      6,
      2,
      9,
      5,
      1,
      10
    ],
    "drawDate": "2025-09-10T00:00:00",
    "drawTime": "17:35",
    "dataSource": "python-scraper",
    "isValid": true,
    "scrapedAt": "2025-09-10T17:57:50.429247"
  },
  {
    "period": "114051282",
    "drawNumbers": [
      7,
      4,
      6,
      3,
      8,
      5,
      1,
      2,
      10,
      9
    ],
    "drawDate": "2025-09-10T00:00:00",
    "drawTime": "17:30",
    "dataSource": "python-scraper",
    "isValid": true,
    "scrapedAt": "2025-09-10T17:57:50.429251"
  },
  {
    "period": "114051281",
    "drawNumbers": [
      2,
      9,
      5,
      3,
      8,
      10,
      6,
      7,
      4,
      1
    ],
    "drawDate": "2025-09-10T00:00:00",
    "drawTime": "17:25",
    "dataSource": "python-scraper",
    "isValid": true,
    "scrapedAt": "2025-09-10T17:57:50.429254"
  },
  {
    "period": "114051280",
    "drawNumbers": [
      1,
      9,
      7,
      4,
      10,
      6,
      2,
      8,
      5,
      3
    ],
    "drawDate": "2025-09-10T00:00:00",
    "drawTime": "17:20",
    "dataSource": "python-scraper",
    "isValid": true,
    "scrapedAt": "2025-09-10T17:57:50.429258"
  },
  {
    "period": "114051279",
    "drawNumbers": [
      4,
      9,
      5,
      7,
      10,
      6,
      3,
      8,
      2,
      1
    ],
    "drawDate": "2025-09-10T00:00:00",
    "drawTime": "17:15",
    "dataSource": "python-scraper",
    "isValid": true,
    "scrapedAt": "2025-09-10T17:57:50.429261"
  },
  {
    "period": "114051278",
    "drawNumbers": [
      6,
      8,
      1,
      5,
      2,
      10,
      4,
      9,
      7,
      3
    ],
    "drawDate": "2025-09-10T00:00:00",
    "drawTime": "17:10",
    "dataSource": "python-scraper",
    "isValid": true,
    "scrapedAt": "2025-09-10T17:57:50.429265"
  },
  {
    "period": "114051277",
    "drawNumbers": [
      10,
      4,
      5,
      6,
      1,
      7,
      3,
      2,
      9,
      8
    ],
    "drawDate": "2025-09-10T00:00:00",
    "drawTime": "17:05",
    "dataSource": "python-scraper",
    "isValid": true,
    "scrapedAt": "2025-09-10T17:57:50.429268"
  },
  {
    "period": "114051276",
    "drawNumbers": [
      5,
      2,
      1,
      9,
      3,
      8,
      7,
      4,
      6,
      10
    ],
    "drawDate": "2025-09-10T00:00:00",
    "drawTime": "17:00",
    "dataSource": "python-scraper",
    "isValid": true,
    "scrapedAt": "2025-09-10T17:57:50.429271"
  },
  {
    "period": "114051275",
    "drawNumbers": [
      10,
      6,
      7,
      5,
      4,
      3,
      8,
      2,
      1,
      9
    ],
    "drawDate": "2025-09-10T00:00:00",
    "drawTime": "16:55",
    "dataSource": "python-scraper",
    "isValid": true,
    "scrapedAt": "2025-09-10T17:57:50.429275"
  },
  {
    "period": "114051274",
    "drawNumbers": [
      2,
      5,
      10,
      3,
      4,
      6,
      9,
      7,
      8,
      1
    ],
    "drawDate": "2025-09-10T00:00:00",
    "drawTime": "16:50",
    "dataSource": "python-scraper",
    "isValid": true,
    "scrapedAt": "2025-09-10T17:57:50.429278"
  },
  {
    "period": "114051273",
    "drawNumbers": [
      2,
      3,
      8,
      10,
      6,
      1,
      4,
      9,
      5,
      7
    ],
    "drawDate": "2025-09-10T00:00:00",
    "drawTime": "16:45",
    "dataSource": "python-scraper",
    "isValid": true,
    "scrapedAt": "2025-09-10T17:57:50.429282"
  },
  {
    "period": "114051272",
    "drawNumbers": [
      10,
      5,
      3,
      8,
      1,
      2,
      9,
      7,
      4,
      6
    ],
    "drawDate": "2025-09-10T00:00:00",
    "drawTime": "16:40",
    "dataSource": "python-scraper",
    "isValid": true,
    "scrapedAt": "2025-09-10T17:57:50.429285"
  },
  {
    "period": "114051271",
    "drawNumbers": [
      5,
      8,
      2,
      7,
      9,
      10,
      4,
      3,
      1,
      6
    ],
    "drawDate": "2025-09-10T00:00:00",
    "drawTime": "16:35",
    "dataSource": "python-scraper",
    "isValid": true,
    "scrapedAt": "2025-09-10T17:57:50.429289"
  },
  {
    "period": "114051270",
    "drawNumbers": [
      10,
      5,
      9,
      8,
      6,
      4,
      2,
      1,
      3,
      7
    ],
    "drawDate": "2025-09-10T00:00:00",
    "drawTime": "16:30",
    "dataSource": "python-scraper",
    "isValid": true,
    "scrapedAt": "2025-09-10T17:57:50.429292"
  },
  {
    "period": "114051269",
    "drawNumbers": [
      2,
      9,
      6,
      4,
      7,
      8,
      5,
      3,
      1,
      10
    ],
    "drawDate": "2025-09-10T00:00:00",
    "drawTime": "16:25",
    "dataSource": "python-scraper",
    "isValid": true,
    "scrapedAt": "2025-09-10T17:57:50.429296"
  },
  {
    "period": "114051268",
    "drawNumbers": [
      7,
      8,
      3,
      5,
      1,
      9,
      10,
      4,
      2,
      6
    ],
    "drawDate": "2025-09-10T00:00:00",
    "drawTime": "16:20",
    "dataSource": "python-scraper",
    "isValid": true,
    "scrapedAt": "2025-09-10T17:57:50.429299"
  },
  {
    "period": "114051267",
    "drawNumbers": [
      6,
      1,
      4,
      9,
      8,
      2,
      7,
      3,
      5,
      10
    ],
    "drawDate": "2025-09-10T00:00:00",
    "drawTime": "16:15",
    "dataSource": "python-scraper",
    "isValid": true,
    "scrapedAt": "2025-09-10T17:57:50.429303"
  },
  {
    "period": "114051266",
    "drawNumbers": [
      5,
      10,
      9,
      8,
      4,
      6,
      1,
      7,
      3,
      2
    ],
    "drawDate": "2025-09-10T00:00:00",
    "drawTime": "16:10",
    "dataSource": "python-scraper",
    "isValid": true,
    "scrapedAt": "2025-09-10T17:57:50.429306"
  },
  {
    "period": "114051265",
    "drawNumbers": [
      10,
      6,
      4,
      2,
      7,
      3,
      1,
      8,
      9,
      5
    ],
    "drawDate": "2025-09-10T00:00:00",
    "drawTime": "16:05",
    "dataSource": "python-scraper",
    "isValid": true,
    "scrapedAt": "2025-09-10T17:57:50.429342"
  },
  {
    "period": "114051264",
    "drawNumbers": [
      1,
      7,
      8,
      10,
      3,
      9,
      4,
      5,
      6,
      2
    ],
    "drawDate": "2025-09-10T00:00:00",
    "drawTime": "16:00",
    "dataSource": "python-scraper",
    "isValid": true,
    "scrapedAt": "2025-09-10T17:57:50.429367"
  },
  {
    "period": "114051263",
    "drawNumbers": [
      2,
      8,
      6,
      3,
      7,
      4,
      5,
      1,
      9,
      10
    ],
    "drawDate": "2025-09-10T00:00:00",
    "drawTime": "15:55",
    "dataSource": "python-scraper",
    "isValid": true,
    "scrapedAt": "2025-09-10T17:57:50.429375"
  },
  {
    "period": "114051262",
    "drawNumbers": [
      5,
      8,
      4,
      1,
      6,
      3,
      2,
      9,
      7,
      10
    ],
    "drawDate": "2025-09-10T00:00:00",
    "drawTime": "15:50",
    "dataSource": "python-scraper",
    "isValid": true,
    "scrapedAt": "2025-09-10T17:57:50.429380"
  },
  {
    "period": "114051261",
    "drawNumbers": [
      1,
      9,
      10,
      6,
      3,
      7,
      2,
      4,
      5,
      8
    ],
    "drawDate": "2025-09-10T00:00:00",
    "drawTime": "15:45",
    "dataSource": "python-scraper",
    "isValid": true,
    "scrapedAt": "2025-09-10T17:57:50.429401"
  },
  {
    "period": "114051260",
    "drawNumbers": [
      9,
      10,
      4,
      3,
      7,
      8,
      2,
      6,
      1,
      5
    ],
    "drawDate": "2025-09-10T00:00:00",
    "drawTime": "15:40",
    "dataSource": "python-scraper",
    "isValid": true,
    "scrapedAt": "2025-09-10T17:57:50.429406"
  },
  {
    "period": "114051259",
    "drawNumbers": [
      5,
      10,
      1,
      2,
      8,
      4,
      7,
      9,
      6,
      3
    ],
    "drawDate": "2025-09-10T00:00:00",
    "drawTime": "15:35",
    "dataSource": "python-scraper",
    "isValid": true,
    "scrapedAt": "2025-09-10T17:57:50.429410"
  },
  {
    "period": "114051258",
    "drawNumbers": [
      2,
      5,
      10,
      4,
      9,
      1,
      8,
      7,
      6,
      3
    ],
    "drawDate": "2025-09-10T00:00:00",
    "drawTime": "15:30",
    "dataSource": "python-scraper",
    "isValid": true,
    "scrapedAt": "2025-09-10T17:57:50.429413"
  },
  {
    "period": "114051257",
    "drawNumbers": [
      6,
      5,
      1,
      7,
      4,
      8,
      9,
      10,
      2,
      3
    ],
    "drawDate": "2025-09-10T00:00:00",
    "drawTime": "15:25",
    "dataSource": "python-scraper",
    "isValid": true,
    "scrapedAt": "2025-09-10T17:57:50.429416"
  },
  {
    "period": "114051256",
    "drawNumbers": [
      5,
      10,
      6,
      8,
      2,
      3,
      9,
      1,
      4,
      7
    ],
    "drawDate": "2025-09-10T00:00:00",
    "drawTime": "15:20",
    "dataSource": "python-scraper",
    "isValid": true,
    "scrapedAt": "2025-09-10T17:57:50.429419"
  },
  {
    "period": "114051255",
    "drawNumbers": [
      6,
      3,
      2,
      7,
      4,
      10,
      5,
      8,
      1,
      9
    ],
    "drawDate": "2025-09-10T00:00:00",
    "drawTime": "15:15",
    "dataSource": "python-scraper",
    "isValid": true,
    "scrapedAt": "2025-09-10T17:57:50.429423"
  },
  {
    "period": "114051254",
    "drawNumbers": [
      10,
      2,
      4,
      9,
      5,
      6,
      3,
      7,
      1,
      8
    ],
    "drawDate": "2025-09-10T00:00:00",
    "drawTime": "15:10",
    "dataSource": "python-scraper",
    "isValid": true,
    "scrapedAt": "2025-09-10T17:57:50.429427"
  },
  {
    "period": "114051253",
    "drawNumbers": [
      8,
      7,
      4,
      2,
      5,
      9,
      6,
      10,
      3,
      1
    ],
    "drawDate": "2025-09-10T00:00:00",
    "drawTime": "15:05",
    "dataSource": "python-scraper",
    "isValid": true,
    "scrapedAt": "2025-09-10T17:57:50.429430"
  },
  {
    "period": "114051252",
    "drawNumbers": [
      9,
      1,
      2,
      8,
      6,
      7,
      4,
      3,
      10,
      5
    ],
    "drawDate": "2025-09-10T00:00:00",
    "drawTime": "15:00",
    "dataSource": "python-scraper",
    "isValid": true,
    "scrapedAt": "2025-09-10T17:57:50.429433"
  },
  {
    "period": "114051251",
    "drawNumbers": [
      8,
      7,
      6,
      5,
      9,
      4,
      10,
      2,
      1,
      3
    ],
    "drawDate": "2025-09-10T00:00:00",
    "drawTime": "14:55",
    "dataSource": "python-scraper",
    "isValid": true,
    "scrapedAt": "2025-09-10T17:57:50.429437"
  },
  {
    "period": "114051250",
    "drawNumbers": [
      1,
      6,
      5,
      4,
      9,
      2,
      7,
      3,
      10,
      8
    ],
    "drawDate": "2025-09-10T00:00:00",
    "drawTime": "14:50",
    "dataSource": "python-scraper",
    "isValid": true,
    "scrapedAt": "2025-09-10T17:57:50.429440"
  },
  {
    "period": "114051249",
    "drawNumbers": [
      4,
      3,
      8,
      5,
      2,
      6,
      1,
      9,
      10,
      7
    ],
    "drawDate": "2025-09-10T00:00:00",
    "drawTime": "14:45",
    "dataSource": "python-scraper",
    "isValid": true,
    "scrapedAt": "2025-09-10T17:57:50.429443"
  },
  {
    "period": "114051248",
    "drawNumbers": [
      5,
      8,
      2,
      6,
      3,
      4,
      9,
      7,
      10,
      1
    ],
    "drawDate": "2025-09-10T00:00:00",
    "drawTime": "14:40",
    "dataSource": "python-scraper",
    "isValid": true,
    "scrapedAt": "2025-09-10T17:57:50.429447"
  },
  {
    "period": "114051247",
    "drawNumbers": [
      8,
      3,
      10,
      6,
      1,
      7,
      9,
      4,
      2,
      5
    ],
    "drawDate": "2025-09-10T00:00:00",
    "drawTime": "14:35",
    "dataSource": "python-scraper",
    "isValid": true,
    "scrapedAt": "2025-09-10T17:57:50.429450"
  },
  {
    "period": "114051246",
    "drawNumbers": [
      8,
      1,
      2,
      5,
      4,
      7,
      9,
      6,
      10,
      3
    ],
    "drawDate": "2025-09-10T00:00:00",
    "drawTime": "14:30",
    "dataSource": "python-scraper",
    "isValid": true,
    "scrapedAt": "2025-09-10T17:57:50.429453"
  },
  {
    "period": "114051245",
    "drawNumbers": [
      8,
      3,
      5,
      10,
      2,
      7,
      1,
      4,
      6,
      9
    ],
    "drawDate": "2025-09-10T00:00:00",
    "drawTime": "14:25",
    "dataSource": "python-scraper",
    "isValid": true,
    "scrapedAt": "2025-09-10T17:57:50.429457"
  },
  {
    "period": "114051244",
    "drawNumbers": [
      8,
      7,
      9,
      5,
      3,
      10,
      1,
      2,
      4,
      6
    ],
    "drawDate": "2025-09-10T00:00:00",
    "drawTime": "14:20",
    "dataSource": "python-scraper",
    "isValid": true,
    "scrapedAt": "2025-09-10T17:57:50.429460"
  },
  {
    "period": "114051243",
    "drawNumbers": [
      6,
      1,
      3,
      7,
      2,
      4,
      5,
      9,
      10,
      8
    ],
    "drawDate": "2025-09-10T00:00:00",
    "drawTime": "14:15",
    "dataSource": "python-scraper",
    "isValid": true,
    "scrapedAt": "2025-09-10T17:57:50.429463"
  },
  {
    "period": "114051242",
    "drawNumbers": [
      1,
      2,
      6,
      8,
      10,
      7,
      9,
      5,
      3,
      4
    ],
    "drawDate": "2025-09-10T00:00:00",
    "drawTime": "14:10",
    "dataSource": "python-scraper",
    "isValid": true,
    "scrapedAt": "2025-09-10T17:57:50.429466"
  },
  {
    "period": "114051241",
    "drawNumbers": [
      8,
      7,
      1,
      2,
      6,
      3,
      9,
      5,
      10,
      4
    ],
    "drawDate": "2025-09-10T00:00:00",
    "drawTime": "14:05",
    "dataSource": "python-scraper",
    "isValid": true,
    "scrapedAt": "2025-09-10T17:57:50.429469"
  },
  {
    "period": "114051240",
    "drawNumbers": [
      8,
      9,
      2,
      7,
      4,
      6,
      10,
      1,
      5,
      3
    ],
    "drawDate": "2025-09-10T00:00:00",
    "drawTime": "14:00",
    "dataSource": "python-scraper",
    "isValid": true,
    "scrapedAt": "2025-09-10T17:57:50.429473"
  },
  {
    "period": "114051239",
    "drawNumbers": [
      3,
      7,
      4,
      9,
      10,
      8,
      2,
      6,
      1,
      5
    ],
    "drawDate": "2025-09-10T00:00:00",
    "drawTime": "13:55",
    "dataSource": "python-scraper",
    "isValid": true,
    "scrapedAt": "2025-09-10T17:57:50.429476"
  },
  {
    "period": "114051238",
    "drawNumbers": [
      4,
      1,
      5,
      7,
      8,
      6,
      10,
      9,
      2,
      3
    ],
    "drawDate": "2025-09-10T00:00:00",
    "drawTime": "13:50",
    "dataSource": "python-scraper",
    "isValid": true,
    "scrapedAt": "2025-09-10T17:57:50.429479"
  },
  {
    "period": "114051237",
    "drawNumbers": [
      6,
      8,
      4,
      7,
      1,
      2,
      10,
      9,
      5,
      3
    ],
    "drawDate": "2025-09-10T00:00:00",
    "drawTime": "13:45",
    "dataSource": "python-scraper",
    "isValid": true,
    "scrapedAt": "2025-09-10T17:57:50.429484"
  },
  {
    "period": "114051236",
    "drawNumbers": [
      1,
      8,
      5,
      6,
      3,
      9,
      10,
      7,
      2,
      4
    ],
    "drawDate": "2025-09-10T00:00:00",
    "drawTime": "13:40",
    "dataSource": "python-scraper",
    "isValid": true,
    "scrapedAt": "2025-09-10T17:57:50.429488"
  },
  {
    "period": "114051235",
    "drawNumbers": [
      4,
      8,
      7,
      3,
      9,
      5,
      2,
      6,
      10,
      1
    ],
    "drawDate": "2025-09-10T00:00:00",
    "drawTime": "13:35",
    "dataSource": "python-scraper",
    "isValid": true,
    "scrapedAt": "2025-09-10T17:57:50.429491"
  },
  {
    "period": "114051234",
    "drawNumbers": [
      7,
      10,
      6,
      2,
      4,
      3,
      8,
      9,
      1,
      5
    ],
    "drawDate": "2025-09-10T00:00:00",
    "drawTime": "13:30",
    "dataSource": "python-scraper",
    "isValid": true,
    "scrapedAt": "2025-09-10T17:57:50.429495"
  },
  {
    "period": "114051233",
    "drawNumbers": [
      1,
      5,
      2,
      9,
      8,
      7,
      6,
      10,
      3,
      4
    ],
    "drawDate": "2025-09-10T00:00:00",
    "drawTime": "13:25",
    "dataSource": "python-scraper",
    "isValid": true,
    "scrapedAt": "2025-09-10T17:57:50.429498"
  },
  {
    "period": "114051232",
    "drawNumbers": [
      6,
      5,
      7,
      4,
      2,
      3,
      9,
      8,
      1,
      10
    ],
    "drawDate": "2025-09-10T00:00:00",
    "drawTime": "13:20",
    "dataSource": "python-scraper",
    "isValid": true,
    "scrapedAt": "2025-09-10T17:57:50.429501"
  },
  {
    "period": "114051231",
    "drawNumbers": [
      3,
      4,
      9,
      8,
      7,
      10,
      2,
      6,
      5,
      1
    ],
    "drawDate": "2025-09-10T00:00:00",
    "drawTime": "13:15",
    "dataSource": "python-scraper",
    "isValid": true,
    "scrapedAt": "2025-09-10T17:57:50.429505"
  },
  {
    "period": "114051230",
    "drawNumbers": [
      10,
      4,
      7,
      2,
      3,
      9,
      6,
      5,
      8,
      1
    ],
    "drawDate": "2025-09-10T00:00:00",
    "drawTime": "13:10",
    "dataSource": "python-scraper",
    "isValid": true,
    "scrapedAt": "2025-09-10T17:57:50.429508"
  },
  {
    "period": "114051229",
    "drawNumbers": [
      8,
      9,
      2,
      3,
      7,
      4,
      10,
      5,
      1,
      6
    ],
    "drawDate": "2025-09-10T00:00:00",
    "drawTime": "13:05",
    "dataSource": "python-scraper",
    "isValid": true,
    "scrapedAt": "2025-09-10T17:57:50.429512"
  },
  {
    "period": "114051228",
    "drawNumbers": [
      2,
      10,
      3,
      5,
      9,
      7,
      1,
      8,
      4,
      6
    ],
    "drawDate": "2025-09-10T00:00:00",
    "drawTime": "13:00",
    "dataSource": "python-scraper",
    "isValid": true,
    "scrapedAt": "2025-09-10T17:57:50.429517"
  },
  {
    "period": "114051227",
    "drawNumbers": [
      10,
      1,
      3,
      7,
      9,
      4,
      8,
      5,
      2,
      6
    ],
    "drawDate": "2025-09-10T00:00:00",
    "drawTime": "12:55",
    "dataSource": "python-scraper",
    "isValid": true,
    "scrapedAt": "2025-09-10T17:57:50.429520"
  },
  {
    "period": "114051226",
    "drawNumbers": [
      7,
      3,
      6,
      9,
      8,
      1,
      10,
      2,
      4,
      5
    ],
    "drawDate": "2025-09-10T00:00:00",
    "drawTime": "12:50",
    "dataSource": "python-scraper",
    "isValid": true,
    "scrapedAt": "2025-09-10T17:57:50.429524"
  },
  {
    "period": "114051225",
    "drawNumbers": [
      10,
      3,
      7,
      4,
      5,
      2,
      8,
      1,
      9,
      6
    ],
    "drawDate": "2025-09-10T00:00:00",
    "drawTime": "12:45",
    "dataSource": "python-scraper",
    "isValid": true,
    "scrapedAt": "2025-09-10T17:57:50.429528"
  },
  {
    "period": "114051224",
    "drawNumbers": [
      5,
      2,
      9,
      1,
      6,
      4,
      8,
      10,
      7,
      3
    ],
    "drawDate": "2025-09-10T00:00:00",
    "drawTime": "12:40",
    "dataSource": "python-scraper",
    "isValid": true,
    "scrapedAt": "2025-09-10T17:57:50.429532"
  },
  {
    "period": "114051223",
    "drawNumbers": [
      10,
      7,
      9,
      6,
      4,
      3,
      1,
      2,
      5,
      8
    ],
    "drawDate": "2025-09-10T00:00:00",
    "drawTime": "12:35",
    "dataSource": "python-scraper",
    "isValid": true,
    "scrapedAt": "2025-09-10T17:57:50.429535"
  },
  {
    "period": "114051222",
    "drawNumbers": [
      3,
      1,
      2,
      8,
      10,
      9,
      5,
      7,
      4,
      6
    ],
    "drawDate": "2025-09-10T00:00:00",
    "drawTime": "12:30",
    "dataSource": "python-scraper",
    "isValid": true,
    "scrapedAt": "2025-09-10T17:57:50.429540"
  },
  {
    "period": "114051221",
    "drawNumbers": [
      10,
      5,
      4,
      6,
      1,
      2,
      7,
      8,
      3,
      9
    ],
    "drawDate": "2025-09-10T00:00:00",
    "drawTime": "12:25",
    "dataSource": "python-scraper",
    "isValid": true,
    "scrapedAt": "2025-09-10T17:57:50.429543"
  },
  {
    "period": "114051220",
    "drawNumbers": [
      1,
      2,
      10,
      8,
      3,
      4,
      5,
      6,
      7,
      9
    ],
    "drawDate": "2025-09-10T00:00:00",
    "drawTime": "12:20",
    "dataSource": "python-scraper",
    "isValid": true,
    "scrapedAt": "2025-09-10T17:57:50.429547"
  },
  {
    "period": "114051219",
    "drawNumbers": [
      4,
      10,
      5,
      9,
      8,
      1,
      2,
      6,
      7,
      3
    ],
    "drawDate": "2025-09-10T00:00:00",
    "drawTime": "12:15",
    "dataSource": "python-scraper",
    "isValid": true,
    "scrapedAt": "2025-09-10T17:57:50.429550"
  },
  {
    "period": "114051218",
    "drawNumbers": [
      1,
      7,
      8,
      9,
      4,
      2,
      3,
      6,
      10,
      5
    ],
    "drawDate": "2025-09-10T00:00:00",
    "drawTime": "12:10",
    "dataSource": "python-scraper",
    "isValid": true,
    "scrapedAt": "2025-09-10T17:57:50.429555"
  },
  {
    "period": "114051217",
    "drawNumbers": [
      1,
      4,
      3,
      6,
      9,
      8,
      7,
      5,
      10,
      2
    ],
    "drawDate": "2025-09-10T00:00:00",
    "drawTime": "12:05",
    "dataSource": "python-scraper",
    "isValid": true,
    "scrapedAt": "2025-09-10T17:57:50.429558"
  },
  {
    "period": "114051216",
    "drawNumbers": [
      4,
      1,
      8,
      9,
      2,
      3,
      5,
      6,
      7,
      10
    ],
    "drawDate": "2025-09-10T00:00:00",
    "drawTime": "12:00",
    "dataSource": "python-scraper",
    "isValid": true,
    "scrapedAt": "2025-09-10T17:57:50.429562"
  },
  {
    "period": "114051215",
    "drawNumbers": [
      2,
      6,
      8,
      10,
      4,
      1,
      3,
      9,
      5,
      7
    ],
    "drawDate": "2025-09-10T00:00:00",
    "drawTime": "11:55",
    "dataSource": "python-scraper",
    "isValid": true,
    "scrapedAt": "2025-09-10T17:57:50.429571"
  },
  {
    "period": "114051214",
    "drawNumbers": [
      8,
      6,
      1,
      5,
      4,
      9,
      10,
      3,
      2,
      7
    ],
    "drawDate": "2025-09-10T00:00:00",
    "drawTime": "11:50",
    "dataSource": "python-scraper",
    "isValid": true,
    "scrapedAt": "2025-09-10T17:57:50.429574"
  },
  {
    "period": "114051213",
    "drawNumbers": [
      10,
      1,
      9,
      6,
      8,
      2,
      3,
      7,
      4,
      5
    ],
    "drawDate": "2025-09-10T00:00:00",
    "drawTime": "11:45",
    "dataSource": "python-scraper",
    "isValid": true,
    "scrapedAt": "2025-09-10T17:57:50.429577"
  },
  {
    "period": "114051212",
    "drawNumbers": [
      9,
      1,
      8,
      4,
      3,
      10,
      6,
      2,
      7,
      5
    ],
    "drawDate": "2025-09-10T00:00:00",
    "drawTime": "11:40",
    "dataSource": "python-scraper",
    "isValid": true,
    "scrapedAt": "2025-09-10T17:57:50.429581"
  },
  {
    "period": "114051211",
    "drawNumbers": [
      1,
      4,
      10,
      6,
      5,
      2,
      7,
      9,
      3,
      8
    ],
    "drawDate": "2025-09-10T00:00:00",
    "drawTime": "11:35",
    "dataSource": "python-scraper",
    "isValid": true,
    "scrapedAt": "2025-09-10T17:57:50.429584"
  },
  {
    "period": "114051210",
    "drawNumbers": [
      7,
      1,
      6,
      2,
      10,
      3,
      5,
      8,
      9,
      4
    ],
    "drawDate": "2025-09-10T00:00:00",
    "drawTime": "11:30",
    "dataSource": "python-scraper",
    "isValid": true,
    "scrapedAt": "2025-09-10T17:57:50.429589"
  },
  {
    "period": "114051209",
    "drawNumbers": [
      5,
      10,
      1,
      9,
      2,
      6,
      4,
      3,
      7,
      8
    ],
    "drawDate": "2025-09-10T00:00:00",
    "drawTime": "11:25",
    "dataSource": "python-scraper",
    "isValid": true,
    "scrapedAt": "2025-09-10T17:57:50.429592"
  },
  {
    "period": "114051208",
    "drawNumbers": [
      2,
      3,
      5,
      4,
      8,
      10,
      7,
      9,
      6,
      1
    ],
    "drawDate": "2025-09-10T00:00:00",
    "drawTime": "11:20",
    "dataSource": "python-scraper",
    "isValid": true,
    "scrapedAt": "2025-09-10T17:57:50.429595"
  },
  {
    "period": "114051207",
    "drawNumbers": [
      2,
      6,
      7,
      8,
      4,
      10,
      9,
      1,
      5,
      3
    ],
    "drawDate": "2025-09-10T00:00:00",
    "drawTime": "11:15",
    "dataSource": "python-scraper",
    "isValid": true,
    "scrapedAt": "2025-09-10T17:57:50.429598"
  },
  {
    "period": "114051206",
    "drawNumbers": [
      10,
      7,
      6,
      3,
      8,
      1,
      4,
      5,
      9,
      2
    ],
    "drawDate": "2025-09-10T00:00:00",
    "drawTime": "11:10",
    "dataSource": "python-scraper",
    "isValid": true,
    "scrapedAt": "2025-09-10T17:57:50.429601"
  },
  {
    "period": "114051205",
    "drawNumbers": [
      9,
      3,
      5,
      4,
      6,
      10,
      1,
      8,
      7,
      2
    ],
    "drawDate": "2025-09-10T00:00:00",
    "drawTime": "11:05",
    "dataSource": "python-scraper",
    "isValid": true,
    "scrapedAt": "2025-09-10T17:57:50.429605"
  },
  {
    "period": "114051204",
    "drawNumbers": [
      6,
      7,
      4,
      3,
      5,
      9,
      2,
      10,
      1,
      8
    ],
    "drawDate": "2025-09-10T00:00:00",
    "drawTime": "11:00",
    "dataSource": "python-scraper",
    "isValid": true,
    "scrapedAt": "2025-09-10T17:57:50.429608"
  },
  {
    "period": "114051203",
    "drawNumbers": [
      2,
      3,
      9,
      1,
      6,
      7,
      5,
      10,
      8,
      4
    ],
    "drawDate": "2025-09-10T00:00:00",
    "drawTime": "10:55",
    "dataSource": "python-scraper",
    "isValid": true,
    "scrapedAt": "2025-09-10T17:57:50.429611"
  },
  {
    "period": "114051202",
    "drawNumbers": [
      9,
      10,
      4,
      7,
      5,
      6,
      8,
      1,
      2,
      3
    ],
    "drawDate": "2025-09-10T00:00:00",
    "drawTime": "10:50",
    "dataSource": "python-scraper",
    "isValid": true,
    "scrapedAt": "2025-09-10T17:57:50.429616"
  },
  {
    "period": "114051201",
    "drawNumbers": [
      5,
      9,
      4,
      2,
      10,
      3,
      8,
      7,
      6,
      1
    ],
    "drawDate": "2025-09-10T00:00:00",
    "drawTime": "10:45",
    "dataSource": "python-scraper",
    "isValid": true,
    "scrapedAt": "2025-09-10T17:57:50.429620"
  },
  {
    "period": "114051200",
    "drawNumbers": [
      10,
      7,
      1,
      4,
      6,
      8,
      9,
      3,
      2,
      5
    ],
    "drawDate": "2025-09-10T00:00:00",
    "drawTime": "10:40",
    "dataSource": "python-scraper",
    "isValid": true,
    "scrapedAt": "2025-09-10T17:57:50.429623"
  },
  {
    "period": "114051199",
    "drawNumbers": [
      9,
      5,
      7,
      10,
      6,
      8,
      3,
      1,
      4,
      2
    ],
    "drawDate": "2025-09-10T00:00:00",
    "drawTime": "10:35",
    "dataSource": "python-scraper",
    "isValid": true,
    "scrapedAt": "2025-09-10T17:57:50.429626"
  },
  {
    "period": "114051198",
    "drawNumbers": [
      5,
      1,
      9,
      4,
      6,
      2,
      10,
      3,
      7,
      8
    ],
    "drawDate": "2025-09-10T00:00:00",
    "drawTime": "10:30",
    "dataSource": "python-scraper",
    "isValid": true,
    "scrapedAt": "2025-09-10T17:57:50.429629"
  },
  {
    "period": "114051197",
    "drawNumbers": [
      10,
      6,
      4,
      1,
      2,
      8,
      5,
      3,
      7,
      9
    ],
    "drawDate": "2025-09-10T00:00:00",
    "drawTime": "10:25",
    "dataSource": "python-scraper",
    "isValid": true,
    "scrapedAt": "2025-09-10T17:57:50.429633"
  },
  {
    "period": "114051196",
    "drawNumbers": [
      10,
      8,
      5,
      3,
      4,
      2,
      6,
      1,
      9,
      7
    ],
    "drawDate": "2025-09-10T00:00:00",
    "drawTime": "10:20",
    "dataSource": "python-scraper",
    "isValid": true,
    "scrapedAt": "2025-09-10T17:57:50.429636"
  },
  {
    "period": "114051195",
    "drawNumbers": [
      1,
      10,
      3,
      8,
      4,
      5,
      2,
      7,
      6,
      9
    ],
    "drawDate": "2025-09-10T00:00:00",
    "drawTime": "10:15",
    "dataSource": "python-scraper",
    "isValid": true,
    "scrapedAt": "2025-09-10T17:57:50.429639"
  },
  {
    "period": "114051194",
    "drawNumbers": [
      6,
      2,
      5,
      4,
      3,
      1,
      8,
      7,
      9,
      10
    ],
    "drawDate": "2025-09-10T00:00:00",
    "drawTime": "10:10",
    "dataSource": "python-scraper",
    "isValid": true,
    "scrapedAt": "2025-09-10T17:57:50.429644"
  },
  {
    "period": "114051193",
    "drawNumbers": [
      7,
      4,
      5,
      6,
      2,
      3,
      1,
      8,
      10,
      9
    ],
    "drawDate": "2025-09-10T00:00:00",
    "drawTime": "10:05",
    "dataSource": "python-scraper",
    "isValid": true,
    "scrapedAt": "2025-09-10T17:57:50.429647"
  },
  {
    "period": "114051192",
    "drawNumbers": [
      3,
      6,
      7,
      8,
      5,
      1,
      10,
      4,
      2,
      9
    ],
    "drawDate": "2025-09-10T00:00:00",
    "drawTime": "10:00",
    "dataSource": "python-scraper",
    "isValid": true,
    "scrapedAt": "2025-09-10T17:57:50.429650"
  },
  {
    "period": "114051191",
    "drawNumbers": [
      5,
      2,
      9,
      10,
      6,
      8,
      1,
      4,
      7,
      3
    ],
    "drawDate": "2025-09-10T00:00:00",
    "drawTime": "09:55",
    "dataSource": "python-scraper",
    "isValid": true,
    "scrapedAt": "2025-09-10T17:57:50.429653"
  },
  {
    "period": "114051190",
    "drawNumbers": [
      8,
      3,
      4,
      1,
      6,
      10,
      9,
      7,
      2,
      5
    ],
    "drawDate": "2025-09-10T00:00:00",
    "drawTime": "09:50",
    "dataSource": "python-scraper",
    "isValid": true,
    "scrapedAt": "2025-09-10T17:57:50.429656"
  },
  {
    "period": "114051189",
    "drawNumbers": [
      4,
      9,
      6,
      2,
      7,
      8,
      3,
      1,
      5,
      10
    ],
    "drawDate": "2025-09-10T00:00:00",
    "drawTime": "09:45",
    "dataSource": "python-scraper",
    "isValid": true,
    "scrapedAt": "2025-09-10T17:57:50.429661"
  },
  {
    "period": "114051188",
    "drawNumbers": [
      2,
      4,
      6,
      8,
      7,
      9,
      1,
      3,
      5,
      10
    ],
    "drawDate": "2025-09-10T00:00:00",
    "drawTime": "09:40",
    "dataSource": "python-scraper",
    "isValid": true,
    "scrapedAt": "2025-09-10T17:57:50.429664"
  },
  {
    "period": "114051187",
    "drawNumbers": [
      9,
      4,
      7,
      1,
      3,
      2,
      5,
      8,
      6,
      10
    ],
    "drawDate": "2025-09-10T00:00:00",
    "drawTime": "09:35",
    "dataSource": "python-scraper",
    "isValid": true,
    "scrapedAt": "2025-09-10T17:57:50.429667"
  },
  {
    "period": "114051186",
    "drawNumbers": [
      1,
      5,
      9,
      8,
      6,
      3,
      4,
      10,
      2,
      7
    ],
    "drawDate": "2025-09-10T00:00:00",
    "drawTime": "09:30",
    "dataSource": "python-scraper",
    "isValid": true,
    "scrapedAt": "2025-09-10T17:57:50.429670"
  },
  {
    "period": "114051185",
    "drawNumbers": [
      2,
      7,
      9,
      3,
      10,
      8,
      5,
      1,
      4,
      6
    ],
    "drawDate": "2025-09-10T00:00:00",
    "drawTime": "09:25",
    "dataSource": "python-scraper",
    "isValid": true,
    "scrapedAt": "2025-09-10T17:57:50.429674"
  },
  {
    "period": "114051184",
    "drawNumbers": [
      4,
      5,
      1,
      8,
      2,
      6,
      7,
      9,
      3,
      10
    ],
    "drawDate": "2025-09-10T00:00:00",
    "drawTime": "09:20",
    "dataSource": "python-scraper",
    "isValid": true,
    "scrapedAt": "2025-09-10T17:57:50.429677"
  },
  {
    "period": "114051183",
    "drawNumbers": [
      1,
      9,
      6,
      7,
      2,
      4,
      8,
      10,
      3,
      5
    ],
    "drawDate": "2025-09-10T00:00:00",
    "drawTime": "09:15",
    "dataSource": "python-scraper",
    "isValid": true,
    "scrapedAt": "2025-09-10T17:57:50.429680"
  },
  {
    "period": "114051182",
    "drawNumbers": [
      9,
      7,
      4,
      1,
      10,
      3,
      8,
      2,
      5,
      6
    ],
    "drawDate": "2025-09-10T00:00:00",
    "drawTime": "09:10",
    "dataSource": "python-scraper",
    "isValid": true,
    "scrapedAt": "2025-09-10T17:57:50.429683"
  },
  {
    "period": "114051181",
    "drawNumbers": [
      1,
      9,
      2,
      5,
      6,
      4,
      10,
      7,
      8,
      3
    ],
    "drawDate": "2025-09-10T00:00:00",
    "drawTime": "09:05",
    "dataSource": "python-scraper",
    "isValid": true,
    "scrapedAt": "2025-09-10T17:57:50.429686"
  },
  {
    "period": "114051180",
    "drawNumbers": [
      3,
      10,
      7,
      9,
      8,
      4,
      5,
      2,
      1,
      6
    ],
    "drawDate": "2025-09-10T00:00:00",
    "drawTime": "09:00",
    "dataSource": "python-scraper",
    "isValid": true,
    "scrapedAt": "2025-09-10T17:57:50.429689"
  },
  {
    "period": "114051179",
    "drawNumbers": [
      5,
      10,
      8,
      7,
      3,
      4,
      2,
      1,
      9,
      6
    ],
    "drawDate": "2025-09-10T00:00:00",
    "drawTime": "08:55",
    "dataSource": "python-scraper",
    "isValid": true,
    "scrapedAt": "2025-09-10T17:57:50.429693"
  },
  {
    "period": "114051178",
    "drawNumbers": [
      10,
      8,
      5,
      6,
      3,
      4,
      7,
      1,
      9,
      2
    ],
    "drawDate": "2025-09-10T00:00:00",
    "drawTime": "08:50",
    "dataSource": "python-scraper",
    "isValid": true,
    "scrapedAt": "2025-09-10T17:57:50.429697"
  },
  {
    "period": "114051177",
    "drawNumbers": [
      4,
      9,
      7,
      3,
      10,
      6,
      5,
      1,
      2,
      8
    ],
    "drawDate": "2025-09-10T00:00:00",
    "drawTime": "08:45",
    "dataSource": "python-scraper",
    "isValid": true,
    "scrapedAt": "2025-09-10T17:57:50.429700"
  },
  {
    "period": "114051176",
    "drawNumbers": [
      9,
      5,
      6,
      4,
      8,
      1,
      2,
      7,
      10,
      3
    ],
    "drawDate": "2025-09-10T00:00:00",
    "drawTime": "08:40",
    "dataSource": "python-scraper",
    "isValid": true,
    "scrapedAt": "2025-09-10T17:57:50.429705"
  },
  {
    "period": "114051175",
    "drawNumbers": [
      1,
      4,
      7,
      10,
      8,
      3,
      5,
      6,
      2,
      9
    ],
    "drawDate": "2025-09-10T00:00:00",
    "drawTime": "08:35",
    "dataSource": "python-scraper",
    "isValid": true,
    "scrapedAt": "2025-09-10T17:57:50.429708"
  },
  {
    "period": "114051174",
    "drawNumbers": [
      2,
      3,
      7,
      9,
      6,
      4,
      5,
      10,
      8,
      1
    ],
    "drawDate": "2025-09-10T00:00:00",
    "drawTime": "08:30",
    "dataSource": "python-scraper",
    "isValid": true,
    "scrapedAt": "2025-09-10T17:57:50.429712"
  },
  {
    "period": "114051173",
    "drawNumbers": [
      2,
      8,
      7,
      9,
      10,
      5,
      6,
      1,
      4,
      3
    ],
    "drawDate": "2025-09-10T00:00:00",
    "drawTime": "08:25",
    "dataSource": "python-scraper",
    "isValid": true,
    "scrapedAt": "2025-09-10T17:57:50.429715"
  },
  {
    "period": "114051172",
    "drawNumbers": [
      10,
      4,
      1,
      7,
      5,
      8,
      6,
      3,
      9,
      2
    ],
    "drawDate": "2025-09-10T00:00:00",
    "drawTime": "08:20",
    "dataSource": "python-scraper",
    "isValid": true,
    "scrapedAt": "2025-09-10T17:57:50.429718"
  },
  {
    "period": "114051171",
    "drawNumbers": [
      4,
      10,
      1,
      9,
      6,
      2,
      3,
      5,
      7,
      8
    ],
    "drawDate": "2025-09-10T00:00:00",
    "drawTime": "08:15",
    "dataSource": "python-scraper",
    "isValid": true,
    "scrapedAt": "2025-09-10T17:57:50.429721"
  },
  {
    "period": "114051170",
    "drawNumbers": [
      2,
      8,
      4,
      5,
      7,
      1,
      9,
      10,
      3,
      6
    ],
    "drawDate": "2025-09-10T00:00:00",
    "drawTime": "08:10",
    "dataSource": "python-scraper",
    "isValid": true,
    "scrapedAt": "2025-09-10T17:57:50.429724"
  },
  {
    "period": "114051169",
    "drawNumbers": [
      6,
      7,
      4,
      5,
      2,
      3,
      10,
      8,
      9,
      1
    ],
    "drawDate": "2025-09-10T00:00:00",
    "drawTime": "08:05",
    "dataSource": "python-scraper",
    "isValid": true,
    "scrapedAt": "2025-09-10T17:57:50.429728"
  },
  {
    "period": "114051168",
    "drawNumbers": [
      4,
      8,
      9,
      5,
      3,
      1,
      7,
      2,
      6,
      10
    ],
    "drawDate": "2025-09-10T00:00:00",
    "drawTime": "08:00",
    "dataSource": "python-scraper",
    "isValid": true,
    "scrapedAt": "2025-09-10T17:57:50.429732"
  },
  {
    "period": "114051167",
    "drawNumbers": [
      6,
      5,
      4,
      3,
      9,
      8,
      2,
      7,
      10,
      1
    ],
    "drawDate": "2025-09-10T00:00:00",
    "drawTime": "07:55",
    "dataSource": "python-scraper",
    "isValid": true,
    "scrapedAt": "2025-09-10T17:57:50.429736"
  },
  {
    "period": "114051166",
    "drawNumbers": [
      5,
      3,
      8,
      10,
      1,
      7,
      9,
      2,
      6,
      4
    ],
    "drawDate": "2025-09-10T00:00:00",
    "drawTime": "07:50",
    "dataSource": "python-scraper",
    "isValid": true,
    "scrapedAt": "2025-09-10T17:57:50.429739"
  },
  {
    "period": "114051165",
    "drawNumbers": [
      5,
      2,
      7,
      6,
      10,
      4,
      1,
      9,
      3,
      8
    ],
    "drawDate": "2025-09-10T00:00:00",
    "drawTime": "07:45",
    "dataSource": "python-scraper",
    "isValid": true,
    "scrapedAt": "2025-09-10T17:57:50.429742"
  },
  {
    "period": "114051164",
    "drawNumbers": [
      8,
      6,
      7,
      2,
      3,
      4,
      1,
      10,
      5,
      9
    ],
    "drawDate": "2025-09-10T00:00:00",
    "drawTime": "07:40",
    "dataSource": "python-scraper",
    "isValid": true,
    "scrapedAt": "2025-09-10T17:57:50.429745"
  },
  {
    "period": "114051163",
    "drawNumbers": [
      8,
      1,
      10,
      7,
      5,
      9,
      6,
      2,
      4,
      3
    ],
    "drawDate": "2025-09-10T00:00:00",
    "drawTime": "07:35",
    "dataSource": "python-scraper",
    "isValid": true,
    "scrapedAt": "2025-09-10T17:57:50.429750"
  },
  {
    "period": "114051162",
    "drawNumbers": [
      3,
      6,
      9,
      1,
      4,
      2,
      8,
      5,
      7,
      10
    ],
    "drawDate": "2025-09-10T00:00:00",
    "drawTime": "07:30",
    "dataSource": "python-scraper",
    "isValid": true,
    "scrapedAt": "2025-09-10T17:57:50.429753"
  },
  {
    "period": "114051161",
    "drawNumbers": [
      5,
      9,
      6,
      3,
      10,
      2,
      8,
      7,
      4,
      1
    ],
    "drawDate": "2025-09-10T00:00:00",
    "drawTime": "07:25",
    "dataSource": "python-scraper",
    "isValid": true,
    "scrapedAt": "2025-09-10T17:57:50.429757"
  },
  {
    "period": "114051160",
    "drawNumbers": [
      10,
      6,
      1,
      8,
      5,
      9,
      3,
      7,
      4,
      2
    ],
    "drawDate": "2025-09-10T00:00:00",
    "drawTime": "07:20",
    "dataSource": "python-scraper",
    "isValid": true,
    "scrapedAt": "2025-09-10T17:57:50.429760"
  },
  {
    "period": "114051159",
    "drawNumbers": [
      6,
      7,
      3,
      9,
      1,
      2,
      5,
      8,
      10,
      4
    ],
    "drawDate": "2025-09-10T00:00:00",
    "drawTime": "07:15",
    "dataSource": "python-scraper",
    "isValid": true,
    "scrapedAt": "2025-09-10T17:57:50.429763"
  },
  {
    "period": "114051158",
    "drawNumbers": [
      5,
      9,
      8,
      2,
      4,
      6,
      3,
      7,
      10,
      1
    ],
    "drawDate": "2025-09-10T00:00:00",
    "drawTime": "07:10",
    "dataSource": "python-scraper",
    "isValid": true,
    "scrapedAt": "2025-09-10T17:57:50.429767"
  },
  {
    "period": "114051157",
    "drawNumbers": [
      2,
      6,
      1,
      4,
      7,
      8,
      9,
      3,
      10,
      5
    ],
    "drawDate": "2025-09-10T00:00:00",
    "drawTime": "07:05",
    "dataSource": "python-scraper",
    "isValid": true,
    "scrapedAt": "2025-09-10T17:57:50.429770"
  }
]